pyPS4Controller/__init__.py
pyPS4Controller/__main__.py
pyPS4Controller/cli.py
pyPS4Controller/controller.py
pyPS4Controller/event_mapping/DefaultMapping.py
pyPS4Controller/event_mapping/Mapping3Bh2b.py
pyPS4Controller/event_mapping/__init__.py
pyPS4Controller-1.2.5.dist-info/LICENCE
pyPS4Controller-1.2.5.dist-info/METADATA
pyPS4Controller-1.2.5.dist-info/WHEEL
pyPS4Controller-1.2.5.dist-info/entry_points.txt
pyPS4Controller-1.2.5.dist-info/top_level.txt
pyPS4Controller-1.2.5.dist-info/RECORD
