Metadata-Version: 2.1
Name: pyPS4Controller
Version: 1.2.5
Summary: Simple hooks for PS4 controller
Home-page: https://github.com/ArturSpirin/pyPS4Controller
Author: Artur Spirin
Author-email: as.no.replies@gmail.com
License: UNKNOWN
Keywords: playstation,ps4,controller,binding,hooks
Platform: UNKNOWN
Classifier: Intended Audience :: Developers
Classifier: Programming Language :: Python :: 2.7
Classifier: Programming Language :: Python :: 3.4
Classifier: Programming Language :: Python :: 3.5
Classifier: Programming Language :: Python :: 3.6
Classifier: Programming Language :: Python :: 3.7
Classifier: Programming Language :: Python :: 3.8
Classifier: License :: OSI Approved :: MIT License
Classifier: Operating System :: POSIX :: Linux
Classifier: Topic :: Software Development :: Libraries
Classifier: Topic :: Software Development :: Libraries :: Python Modules
Classifier: Topic :: Utilities
